LICENSE
MANIFEST.in
README.md
pyproject.toml
setup.py
src/cdktn_provider_aws/__init__.py
src/cdktn_provider_aws/py.typed
src/cdktn_provider_aws.egg-info/PKG-INFO
src/cdktn_provider_aws.egg-info/SOURCES.txt
src/cdktn_provider_aws.egg-info/dependency_links.txt
src/cdktn_provider_aws.egg-info/requires.txt
src/cdktn_provider_aws.egg-info/top_level.txt
src/cdktn_provider_aws/_jsii/__init__.py
src/cdktn_provider_aws/_jsii/provider-aws@21.23.0.jsii.tgz
src/cdktn_provider_aws/accessanalyzer_analyzer/__init__.py
src/cdktn_provider_aws/accessanalyzer_archive_rule/__init__.py
src/cdktn_provider_aws/account_alternate_contact/__init__.py
src/cdktn_provider_aws/account_primary_contact/__init__.py
src/cdktn_provider_aws/account_region/__init__.py
src/cdktn_provider_aws/acm_certificate/__init__.py
src/cdktn_provider_aws/acm_certificate_validation/__init__.py
src/cdktn_provider_aws/acmpca_certificate/__init__.py
src/cdktn_provider_aws/acmpca_certificate_authority/__init__.py
src/cdktn_provider_aws/acmpca_certificate_authority_certificate/__init__.py
src/cdktn_provider_aws/acmpca_permission/__init__.py
src/cdktn_provider_aws/acmpca_policy/__init__.py
src/cdktn_provider_aws/alb/__init__.py
src/cdktn_provider_aws/alb_listener/__init__.py
src/cdktn_provider_aws/alb_listener_certificate/__init__.py
src/cdktn_provider_aws/alb_listener_rule/__init__.py
src/cdktn_provider_aws/alb_target_group/__init__.py
src/cdktn_provider_aws/alb_target_group_attachment/__init__.py
src/cdktn_provider_aws/ami/__init__.py
src/cdktn_provider_aws/ami_copy/__init__.py
src/cdktn_provider_aws/ami_from_instance/__init__.py
src/cdktn_provider_aws/ami_launch_permission/__init__.py
src/cdktn_provider_aws/amplify_app/__init__.py
src/cdktn_provider_aws/amplify_backend_environment/__init__.py
src/cdktn_provider_aws/amplify_branch/__init__.py
src/cdktn_provider_aws/amplify_domain_association/__init__.py
src/cdktn_provider_aws/amplify_webhook/__init__.py
src/cdktn_provider_aws/api_gateway_account/__init__.py
src/cdktn_provider_aws/api_gateway_api_key/__init__.py
src/cdktn_provider_aws/api_gateway_authorizer/__init__.py
src/cdktn_provider_aws/api_gateway_base_path_mapping/__init__.py
